{
  "unversionedId": "how_tos/nfts/send_nft",
  "id": "how_tos/nfts/send_nft",
  "title": "Send NFT",
  "description": "How to send NFT to another address",
  "source": "@site/docs/how_tos/nfts/send_nft.mdx",
  "sourceDirName": "how_tos/nfts",
  "slug": "/how_tos/nfts/send_nft",
  "permalink": "/iota-sdk/how_tos/nfts/send_nft",
  "draft": false,
  "editUrl": "https://github.com/iotaledger/iota-sdk/edit/documentation/sdk/docs/how_tos/nfts/send_nft.mdx",
  "tags": [],
  "version": "current",
  "frontMatter": {
    "title": "Send NFT",
    "description": "How to send NFT to another address",
    "image": "/img/logo/iota_mark_light.png",
    "keywords": [
      "how to",
      "send",
      "nft",
      "nodejs",
      "python",
      "rust"
    ]
  },
  "sidebar": "docs",
  "previous": {
    "title": "Burn NFT",
    "permalink": "/iota-sdk/how_tos/nfts/burn_nft"
  },
  "next": {
    "title": "Troubleshooting",
    "permalink": "/iota-sdk/troubleshooting"
  }
}